dash_vtk/Algorithm.py
dash_vtk/Calculator.py
dash_vtk/CellData.py
dash_vtk/DataArray.py
dash_vtk/FieldData.py
dash_vtk/GeometryRepresentation.py
dash_vtk/GlyphRepresentation.py
dash_vtk/ImageData.py
dash_vtk/Mesh.py
dash_vtk/PointCloudRepresentation.py
dash_vtk/PointData.py
dash_vtk/PolyData.py
dash_vtk/Reader.py
dash_vtk/ShareDataSet.py
dash_vtk/SliceRepresentation.py
dash_vtk/View.py
dash_vtk/Volume.py
dash_vtk/VolumeController.py
dash_vtk/VolumeDataRepresentation.py
dash_vtk/VolumeRepresentation.py
dash_vtk/__init__.py
dash_vtk/_imports_.py
dash_vtk/async-ReactVTK.js
dash_vtk/async-ReactVTK.js.map
dash_vtk/dash_vtk.min.js
dash_vtk/dash_vtk.min.js.map
dash_vtk/metadata.json
dash_vtk/package-info.json
dash_vtk/utils/__init__.py
dash_vtk/utils/vtk.py
dash_vtk-0.0.9.dist-info/LICENSE
dash_vtk-0.0.9.dist-info/METADATA
dash_vtk-0.0.9.dist-info/WHEEL
dash_vtk-0.0.9.dist-info/top_level.txt
dash_vtk-0.0.9.dist-info/RECORD
